doit_cli/__init__.py
doit_cli/main.py
doit_cli/cli/__init__.py
doit_cli/cli/analytics_command.py
doit_cli/cli/constitution_command.py
doit_cli/cli/context_command.py
doit_cli/cli/diagram_command.py
doit_cli/cli/fixit_command.py
doit_cli/cli/hooks_command.py
doit_cli/cli/init_command.py
doit_cli/cli/memory_command.py
doit_cli/cli/provider_command.py
doit_cli/cli/roadmapit_command.py
doit_cli/cli/roadmapit_impl.py
doit_cli/cli/status_command.py
doit_cli/cli/sync_prompts_command.py
doit_cli/cli/team_command.py
doit_cli/cli/validate_command.py
doit_cli/cli/verify_command.py
doit_cli/cli/workflow_mixin.py
doit_cli/cli/xref_command.py
doit_cli/formatters/__init__.py
doit_cli/formatters/base.py
doit_cli/formatters/json_formatter.py
doit_cli/formatters/markdown_formatter.py
doit_cli/formatters/rich_formatter.py
doit_cli/models/__init__.py
doit_cli/models/agent.py
doit_cli/models/analytics_models.py
doit_cli/models/cleanup_models.py
doit_cli/models/context_config.py
doit_cli/models/crossref_models.py
doit_cli/models/diagram_models.py
doit_cli/models/fixit_models.py
doit_cli/models/github_epic.py
doit_cli/models/github_feature.py
doit_cli/models/hook_config.py
doit_cli/models/milestone.py
doit_cli/models/priority.py
doit_cli/models/project.py
doit_cli/models/provider_models.py
doit_cli/models/results.py
doit_cli/models/roadmap.py
doit_cli/models/search_models.py
doit_cli/models/status_models.py
doit_cli/models/sync_metadata.py
doit_cli/models/sync_models.py
doit_cli/models/sync_operation.py
doit_cli/models/team_errors.py
doit_cli/models/team_models.py
doit_cli/models/template.py
doit_cli/models/validation_models.py
doit_cli/models/wizard_models.py
doit_cli/models/workflow_models.py
doit_cli/prompts/__init__.py
doit_cli/prompts/fixit_prompts.py
doit_cli/prompts/interactive.py
doit_cli/rules/__init__.py
doit_cli/rules/builtin_rules.py
doit_cli/services/__init__.py
doit_cli/services/access_service.py
doit_cli/services/agent_detector.py
doit_cli/services/analytics_service.py
doit_toolkit_cli-0.1.16.dist-info/METADATA
doit_toolkit_cli-0.1.16.dist-info/WHEEL
doit_toolkit_cli-0.1.16.dist-info/entry_points.txt
doit_toolkit_cli-0.1.16.dist-info/licenses/LICENSE
doit_toolkit_cli-0.1.16.dist-info/RECORD
