Metadata-Version: 2.4
Name: doit-toolkit-cli
Version: 0.1.16
Summary: Doit CLI - A tool to bootstrap your projects for Spec-Driven Development (SDD).
Project-URL: Homepage, https://github.com/seanbarlow/doit
Project-URL: Documentation, https://github.com/seanbarlow/doit#readme
Project-URL: Repository, https://github.com/seanbarlow/doit.git
Project-URL: Issues, https://github.com/seanbarlow/doit/issues
Author-email: Sean Barlow <sbarlow@barlowtech.com>
License: MIT
License-File: LICENSE
Keywords: ai,cli,development-workflow,scaffolding,sdd,spec-driven-development
Classifier: Development Status :: 4 - Beta
Classifier: Environment :: Console
Classifier: Intended Audience :: Developers
Classifier: License :: OSI Approved :: MIT License
Classifier: Operating System :: OS Independent
Classifier: Programming Language :: Python :: 3
Classifier: Programming Language :: Python :: 3.11
Classifier: Programming Language :: Python :: 3.12
Classifier: Topic :: Software Development :: Code Generators
Classifier: Topic :: Software Development :: Quality Assurance
Requires-Python: >=3.11
Requires-Dist: httpx[socks]
Requires-Dist: platformdirs
Requires-Dist: pyyaml>=6.0
Requires-Dist: readchar
Requires-Dist: rich>=13.0.0
Requires-Dist: truststore>=0.10.4
Requires-Dist: typer>=0.9.0
Requires-Dist: watchdog>=3.0.0
Provides-Extra: advanced
Requires-Dist: scikit-learn>=1.3.0; extra == 'advanced'
Requires-Dist: tiktoken>=0.5.0; extra == 'advanced'
Provides-Extra: dev
Requires-Dist: pytest-tmp-files>=0.0.2; extra == 'dev'
Requires-Dist: pytest>=7.0.0; extra == 'dev'
